{
  "schemaVersion": 1,
  "alphaclawVersion": "0.9.15-starfoundry.1",
  "openclawVersion": "2026.5.6",
  "source": {
    "openclawPackage": "openclaw",
    "openclawGitRef": "v2026.5.6",
    "upstreamCatalogs": [
      {
        "kind": "channel",
        "path": "scripts/lib/official-external-channel-catalog.json",
        "url": "https://github.com/openclaw/openclaw/blob/v2026.5.6/scripts/lib/official-external-channel-catalog.json"
      },
      {
        "kind": "plugin",
        "path": "scripts/lib/official-external-plugin-catalog.json",
        "url": "https://github.com/openclaw/openclaw/blob/v2026.5.6/scripts/lib/official-external-plugin-catalog.json"
      },
      {
        "kind": "provider",
        "path": "scripts/lib/official-external-provider-catalog.json",
        "url": "https://github.com/openclaw/openclaw/blob/v2026.5.6/scripts/lib/official-external-provider-catalog.json"
      }
    ]
  },
  "managedPlugins": {
    "wecom-openclaw-plugin": {
      "kind": "channel",
      "package": "@wecom/wecom-openclaw-plugin",
      "version": "2026.4.23",
      "pluginId": "wecom-openclaw-plugin",
      "channelId": "wecom",
      "description": "OpenClaw WeCom channel plugin by the Tencent WeCom team.",
      "source": "external",
      "install": {
        "npmSpec": "@wecom/wecom-openclaw-plugin",
        "exactNpmSpec": "@wecom/wecom-openclaw-plugin@2026.4.23",
        "defaultChoice": "npm"
      }
    },
    "openclaw-plugin-yuanbao": {
      "kind": "channel",
      "package": "openclaw-plugin-yuanbao",
      "version": "2.11.0",
      "pluginId": "openclaw-plugin-yuanbao",
      "channelId": "yuanbao",
      "description": "OpenClaw Yuanbao channel plugin by the Tencent Yuanbao team.",
      "source": "external",
      "install": {
        "npmSpec": "openclaw-plugin-yuanbao",
        "exactNpmSpec": "openclaw-plugin-yuanbao@2.11.0",
        "defaultChoice": "npm"
      }
    },
    "bluebubbles": {
      "kind": "channel",
      "package": "@openclaw/bluebubbles",
      "version": "2026.5.6",
      "pluginId": "bluebubbles",
      "channelId": "bluebubbles",
      "description": "OpenClaw BlueBubbles channel plugin",
      "source": "official",
      "install": {
        "npmSpec": "@openclaw/bluebubbles",
        "exactNpmSpec": "@openclaw/bluebubbles@2026.5.6",
        "defaultChoice": "npm",
        "minHostVersion": ">=2026.4.10"
      }
    },
    "discord": {
      "kind": "channel",
      "package": "@openclaw/discord",
      "version": "2026.5.6",
      "pluginId": "discord",
      "channelId": "discord",
      "description": "OpenClaw Discord channel plugin",
      "source": "official",
      "install": {
        "npmSpec": "@openclaw/discord",
        "exactNpmSpec": "@openclaw/discord@2026.5.6",
        "defaultChoice": "npm",
        "minHostVersion": ">=2026.4.10"
      }
    },
    "feishu": {
      "kind": "channel",
      "package": "@openclaw/feishu",
      "version": "2026.5.6",
      "pluginId": "feishu",
      "channelId": "feishu",
      "description": "OpenClaw Feishu/Lark channel plugin",
      "source": "official",
      "install": {
        "npmSpec": "@openclaw/feishu",
        "exactNpmSpec": "@openclaw/feishu@2026.5.6",
        "defaultChoice": "npm",
        "minHostVersion": ">=2026.4.25"
      }
    },
    "googlechat": {
      "kind": "channel",
      "package": "@openclaw/googlechat",
      "version": "2026.5.6",
      "pluginId": "googlechat",
      "channelId": "googlechat",
      "description": "OpenClaw Google Chat channel plugin",
      "source": "official",
      "install": {
        "npmSpec": "@openclaw/googlechat",
        "exactNpmSpec": "@openclaw/googlechat@2026.5.6",
        "defaultChoice": "npm",
        "minHostVersion": ">=2026.4.10"
      }
    },
    "line": {
      "kind": "channel",
      "package": "@openclaw/line",
      "version": "2026.5.6",
      "pluginId": "line",
      "channelId": "line",
      "description": "OpenClaw LINE channel plugin",
      "source": "official",
      "install": {
        "npmSpec": "@openclaw/line",
        "exactNpmSpec": "@openclaw/line@2026.5.6",
        "defaultChoice": "npm",
        "minHostVersion": ">=2026.4.10"
      }
    },
    "msteams": {
      "kind": "channel",
      "package": "@openclaw/msteams",
      "version": "2026.5.6",
      "pluginId": "msteams",
      "channelId": "msteams",
      "description": "OpenClaw Microsoft Teams channel plugin",
      "source": "official",
      "install": {
        "npmSpec": "@openclaw/msteams",
        "exactNpmSpec": "@openclaw/msteams@2026.5.6",
        "defaultChoice": "npm",
        "minHostVersion": ">=2026.4.10"
      }
    },
    "nextcloud-talk": {
      "kind": "channel",
      "package": "@openclaw/nextcloud-talk",
      "version": "2026.5.6",
      "pluginId": "nextcloud-talk",
      "channelId": "nextcloud-talk",
      "description": "OpenClaw Nextcloud Talk channel plugin",
      "source": "official",
      "install": {
        "npmSpec": "@openclaw/nextcloud-talk",
        "exactNpmSpec": "@openclaw/nextcloud-talk@2026.5.6",
        "defaultChoice": "npm",
        "minHostVersion": ">=2026.4.10"
      }
    },
    "nostr": {
      "kind": "channel",
      "package": "@openclaw/nostr",
      "version": "2026.5.6",
      "pluginId": "nostr",
      "channelId": "nostr",
      "description": "OpenClaw Nostr channel plugin for NIP-04 encrypted DMs",
      "source": "official",
      "install": {
        "npmSpec": "@openclaw/nostr",
        "exactNpmSpec": "@openclaw/nostr@2026.5.6",
        "defaultChoice": "npm",
        "minHostVersion": ">=2026.4.10"
      }
    },
    "qqbot": {
      "kind": "channel",
      "package": "@openclaw/qqbot",
      "version": "2026.5.6",
      "pluginId": "qqbot",
      "channelId": "qqbot",
      "description": "OpenClaw QQ Bot channel plugin",
      "source": "official",
      "install": {
        "npmSpec": "@openclaw/qqbot",
        "exactNpmSpec": "@openclaw/qqbot@2026.5.6",
        "defaultChoice": "npm",
        "minHostVersion": ">=2026.4.10"
      }
    },
    "synology-chat": {
      "kind": "channel",
      "package": "@openclaw/synology-chat",
      "version": "2026.5.6",
      "pluginId": "synology-chat",
      "channelId": "synology-chat",
      "description": "Synology Chat channel plugin for OpenClaw",
      "source": "official",
      "install": {
        "npmSpec": "@openclaw/synology-chat",
        "exactNpmSpec": "@openclaw/synology-chat@2026.5.6",
        "defaultChoice": "npm",
        "minHostVersion": ">=2026.4.10"
      }
    },
    "tlon": {
      "kind": "channel",
      "package": "@openclaw/tlon",
      "version": "2026.5.6",
      "pluginId": "tlon",
      "channelId": "tlon",
      "description": "OpenClaw Tlon/Urbit channel plugin",
      "source": "official",
      "install": {
        "npmSpec": "@openclaw/tlon",
        "exactNpmSpec": "@openclaw/tlon@2026.5.6",
        "defaultChoice": "npm",
        "minHostVersion": ">=2026.4.10"
      }
    },
    "twitch": {
      "kind": "channel",
      "package": "@openclaw/twitch",
      "version": "2026.5.6",
      "pluginId": "twitch",
      "channelId": "twitch",
      "description": "OpenClaw Twitch channel plugin",
      "source": "official",
      "install": {
        "npmSpec": "@openclaw/twitch",
        "exactNpmSpec": "@openclaw/twitch@2026.5.6",
        "defaultChoice": "npm",
        "minHostVersion": ">=2026.4.10"
      }
    },
    "whatsapp": {
      "kind": "channel",
      "package": "@openclaw/whatsapp",
      "version": "2026.5.6",
      "pluginId": "whatsapp",
      "channelId": "whatsapp",
      "description": "OpenClaw WhatsApp channel plugin",
      "source": "official",
      "install": {
        "npmSpec": "@openclaw/whatsapp",
        "exactNpmSpec": "@openclaw/whatsapp@2026.5.6",
        "defaultChoice": "npm",
        "minHostVersion": ">=2026.4.25"
      }
    },
    "zalo": {
      "kind": "channel",
      "package": "@openclaw/zalo",
      "version": "2026.5.6",
      "pluginId": "zalo",
      "channelId": "zalo",
      "description": "OpenClaw Zalo channel plugin",
      "source": "official",
      "install": {
        "npmSpec": "@openclaw/zalo",
        "exactNpmSpec": "@openclaw/zalo@2026.5.6",
        "defaultChoice": "npm",
        "minHostVersion": ">=2026.4.10"
      }
    },
    "zalouser": {
      "kind": "channel",
      "package": "@openclaw/zalouser",
      "version": "2026.5.6",
      "pluginId": "zalouser",
      "channelId": "zalouser",
      "description": "OpenClaw Zalo Personal Account plugin via native zca-js integration",
      "source": "official",
      "install": {
        "npmSpec": "@openclaw/zalouser",
        "exactNpmSpec": "@openclaw/zalouser@2026.5.6",
        "defaultChoice": "npm",
        "minHostVersion": ">=2026.4.10"
      }
    },
    "acpx": {
      "kind": "plugin",
      "package": "@openclaw/acpx",
      "version": "2026.5.6",
      "pluginId": "acpx",
      "description": "OpenClaw ACP runtime backend",
      "source": "official",
      "install": {
        "npmSpec": "@openclaw/acpx",
        "exactNpmSpec": "@openclaw/acpx@2026.5.6",
        "defaultChoice": "npm",
        "minHostVersion": ">=2026.4.25"
      }
    },
    "brave": {
      "kind": "plugin",
      "package": "@openclaw/brave-plugin",
      "version": "2026.5.6",
      "pluginId": "brave",
      "webSearchProviderIds": [
        "brave"
      ],
      "description": "OpenClaw Brave plugin",
      "source": "official",
      "install": {
        "npmSpec": "@openclaw/brave-plugin",
        "exactNpmSpec": "@openclaw/brave-plugin@2026.5.6",
        "defaultChoice": "npm",
        "minHostVersion": ">=2026.4.10"
      }
    },
    "diagnostics-otel": {
      "kind": "plugin",
      "package": "@openclaw/diagnostics-otel",
      "version": "2026.5.6",
      "pluginId": "diagnostics-otel",
      "description": "OpenClaw diagnostics OpenTelemetry exporter",
      "source": "official",
      "install": {
        "npmSpec": "@openclaw/diagnostics-otel",
        "exactNpmSpec": "@openclaw/diagnostics-otel@2026.5.6",
        "defaultChoice": "npm",
        "minHostVersion": ">=2026.4.25"
      }
    },
    "diagnostics-prometheus": {
      "kind": "plugin",
      "package": "@openclaw/diagnostics-prometheus",
      "version": "2026.5.6",
      "pluginId": "diagnostics-prometheus",
      "description": "OpenClaw diagnostics Prometheus exporter",
      "source": "official",
      "install": {
        "npmSpec": "@openclaw/diagnostics-prometheus",
        "exactNpmSpec": "@openclaw/diagnostics-prometheus@2026.5.6",
        "defaultChoice": "npm",
        "minHostVersion": ">=2026.4.25"
      }
    },
    "diffs": {
      "kind": "plugin",
      "package": "@openclaw/diffs",
      "version": "2026.5.6",
      "pluginId": "diffs",
      "description": "OpenClaw diff viewer plugin",
      "source": "official",
      "install": {
        "npmSpec": "@openclaw/diffs",
        "exactNpmSpec": "@openclaw/diffs@2026.5.6",
        "defaultChoice": "npm",
        "minHostVersion": ">=2026.4.30"
      }
    },
    "google-meet": {
      "kind": "plugin",
      "package": "@openclaw/google-meet",
      "version": "2026.5.6",
      "pluginId": "google-meet",
      "description": "OpenClaw Google Meet participant plugin",
      "source": "official",
      "install": {
        "npmSpec": "@openclaw/google-meet",
        "exactNpmSpec": "@openclaw/google-meet@2026.5.6",
        "defaultChoice": "npm",
        "minHostVersion": ">=2026.4.20"
      }
    },
    "lobster": {
      "kind": "plugin",
      "package": "@openclaw/lobster",
      "version": "2026.5.6",
      "pluginId": "lobster",
      "description": "Lobster workflow tool plugin (typed pipelines + resumable approvals)",
      "source": "official",
      "install": {
        "npmSpec": "@openclaw/lobster",
        "exactNpmSpec": "@openclaw/lobster@2026.5.6",
        "defaultChoice": "npm",
        "minHostVersion": ">=2026.4.25"
      }
    },
    "memory-lancedb": {
      "kind": "plugin",
      "package": "@openclaw/memory-lancedb",
      "version": "2026.5.6",
      "pluginId": "memory-lancedb",
      "description": "OpenClaw LanceDB-backed long-term memory plugin with auto-recall/capture",
      "source": "official",
      "install": {
        "npmSpec": "@openclaw/memory-lancedb",
        "exactNpmSpec": "@openclaw/memory-lancedb@2026.5.6",
        "defaultChoice": "npm",
        "minHostVersion": ">=2026.4.10"
      }
    },
    "voice-call": {
      "kind": "plugin",
      "package": "@openclaw/voice-call",
      "version": "2026.5.6",
      "pluginId": "voice-call",
      "description": "OpenClaw voice-call plugin",
      "source": "official",
      "install": {
        "npmSpec": "@openclaw/voice-call",
        "exactNpmSpec": "@openclaw/voice-call@2026.5.6",
        "defaultChoice": "npm",
        "minHostVersion": ">=2026.4.10"
      }
    },
    "codex": {
      "kind": "provider",
      "package": "@openclaw/codex",
      "version": "2026.5.6",
      "pluginId": "codex",
      "providerIds": [
        "codex"
      ],
      "description": "OpenClaw Codex harness and model provider plugin",
      "source": "official",
      "install": {
        "npmSpec": "@openclaw/codex",
        "exactNpmSpec": "@openclaw/codex@2026.5.6",
        "defaultChoice": "npm",
        "minHostVersion": ">=2026.5.1-beta.1"
      }
    }
  }
}
